Workbook

Sheet Resumo
A1: RESIDÊNCIA Q22 · L8 — PLANILHA DE CUSTOS E MATERIAIS
A2: Gerada automaticamente a partir dos dados do painel de obra · NÃO editar à mão
A3: Gerada em 27/07/2026 00:49 (BRT)
A5: INDICADOR | B5: VALOR | D5: OBSERVAÇÃO
A6: Área construída | B6: 183 | C6: m² | D6: térreo 75 + garagem 27,5 + superior 62 + extensão 18
A7: Estimativa — faixa baixa | B7: =SUM(Etapas!C3:C15) | D7: soma das 13 etapas
A8: Estimativa — faixa alta | B8: =SUM(Etapas!D3:D15) | D8: soma das 13 etapas
A9: Custo/m² — baixo | B9: =B7/B6 | D9: referência CUB-SP R8-N: R$ 2.129,86
A10: Custo/m² — alto | B10: =B8/B6 | D10: diferença = sistemas premium (bomba de calor, automação, resinados)
A11: Total cotado/contratado | B11: =SUM(Cotações!K2:K2) | D11: soma de tudo lançado no site
A12: ├ material | B12: =SUMIF(Cotações!C2:C2,"<>mão de obra",Cotações!K2:K2)
A13: └ mão de obra | B13: =SUMIF(Cotações!C2:C2,"mão de obra",Cotações!K2:K2) | D13: empreiteiros/equipes cotados por etapa
A14: Custo real informado | B14: =SUM(Etapas!I3:I15) | D14: digitado na aba Etapas do site
A15: Cotações registradas | B15: =COUNTA(Cotações!A2:A2) | D15: cada lançamento = 1 commit no repositório
A16: Avanço geral (ponderado por custo) | B16: =IFERROR(SUMPRODUCT(Etapas!H3:H15,Etapas!E3:E15)/SUM(Etapas!E3:E15),0) | D16: ponderado pela média da faixa de cada etapa
A17: Etapas concluídas | B17: =COUNTIF(Etapas!G3:G15,"concluída") | C17: de 13
A19: SISTEMA CONSTRUTIVO (revisão atual)
A20: Paredes estruturais | B20: Monolev ~320 m² líquidos — perímetro + estruturais do térreo (divisa da garagem, testada)
A21: Divisórias em Lightwall | B21: Lightwall 2P 90 mm ~100 m²: todo o pav. superior (conceito mezanino) + caixas do lavabo e do banheiro do térreo — nenhuma delas é estrutural
A22: Lajes | B22: Vigotas + EPS ~86 m² — SÓ pisos (superior, extensão, técnica). Não há laje de forro.
A23: Forro | B23: Madeira acompanhando o telhado ~45 m² (mezanino + vão duplo) · gesso+EPS nivelado ~47 m² (demais)
A24: Cobertura | B24: 3 treliças galvanizadas a fogo @3,25 m (banzos paralelos h=0,40, degrau triangulado) + terças Ue 100 · ~1,0 t
A25: Faixa NE (1,20) | B25: Da fachada ao fundo: portinha (0,80) · Luz 1 = jardim de inverno c/ parede verde e janelão 3,50 (4,10) · PAREDE CEGA · Luz 2 = varal (4,10) · lavanderia + área técnica acima (4,00, único trecho coberto até a divisa)
A26: Fundação | B26: Radier ~103 m²
A27: Exaustão da ilha | B27: Plenum no forro c/ 2 frestas lineares de 30 mm + luz integrada · 1.100 m³/h · duto Ø250 · motor inline REMOTO na área técnica (32-38 dB(A) na cozinha) · liga sozinho pelo consumo do circuito do Invisacook
A28: Área técnica | B28: ABERTA (sem porta, só portão-gradil) — garante ar para a bomba de calor · acesso por escada marinheiro na parede da Luz 2 · equipamentos em IP65
A29: COMO USAR | B29: Calhas retangulares 150×100 nas 2 bordas longas (i=0,5% p/ o fundo) + 2 condutores Ø100 · I=172 mm/h · 108 m² de captação · rufos em chapa galv. #24
A30: Esta planilha é um EXPORT do painel de obra e é regerada a cada cotação lançada no site. Edições feitas aqui serão perdidas na próxima geração — lance tudo pelo site (pvizioli.github.io/projeto_casa_pedro) para que vire commit e volte para cá.
A33: Térreo — faixa SO | B33: Lavabo 1,50 × 1,50 no canto da garagem c/ o corredor (janela p/ o corredor) · despensa (1,50 × 1,10) + bancada + banheiro completo (1,50 × 2,50, sem box) no fundo, porta ÚNICA p/ a área gourmet

Sheet Etapas
A1: ETAPAS DA OBRA — 13 FASES
A2: # | B2: Etapa | C2: Estim. baixa | D2: Estim. alta | E2: Média | F2: % do total | G2: Status | H2: Avanço | I2: Custo real | J2: Cotado material | K2: Cotado mão de obra | L2: Cotado total | M2: Δ vs. alta | N2: Observação
A3: 1 | B3: Projetos, sondagem e aprovações | C3: 34000 | D3: 78000 | E3: =(C3+D3)/2 | F3: =IFERROR(E3/$E$16,0) | G3: não iniciada | H3: 0 | I3: 0 | J3: =SUMIFS(Cotações!$K$2:$K$2,Cotações!$G$2:$G$2,$A3,Cotações!$C$2:$C$2,"<>mão de obra") | K3: =SUMIFS(Cotações!$K$2:$K$2,Cotações!$G$2:$G$2,$A3,Cotações!$C$2:$C$2,"mão de obra") | L3: =J3+K3 | M3: =IF(L3=0,"",D3-L3) | N3: arquitetônico (legal+executivo) 12–27k · estrutural 5–12k · complementares 5–10k · AVAC 1,5–3k · SPT 2–4k · ART/RRT 1–2k · aprovações 1,5–4k · RT de execução 8–25k (10 meses) — detalhado na categoria Projetos e Serviços Técnicos
A4: 2 | B4: Fundação (radier 103 m²) + muro de divisa 210 m² | C4: 50500 | D4: 78500 | E4: =(C4+D4)/2 | F4: =IFERROR(E4/$E$16,0) | G4: não iniciada | H4: 0 | I4: 0 | J4: =SUMIFS(Cotações!$K$2:$K$2,Cotações!$G$2:$G$2,$A4,Cotações!$C$2:$C$2,"<>mão de obra") | K4: =SUMIFS(Cotações!$K$2:$K$2,Cotações!$G$2:$G$2,$A4,Cotações!$C$2:$C$2,"mão de obra") | L4: =J4+K4 | M4: =IF(L4=0,"",D4-L4) | N4: radier inclui eletroduto da ilha e hidráulica embutida · muro pré-moldado (placa) 210 m² (2×30,00 laterais + 10,00 fundo, h=3,00) — sistema mais econômico do mercado, ~30% mais barato que alvenaria convencional
A5: 3 | B5: Estrutura metálica | C5: 28000 | D5: 42000 | E5: =(C5+D5)/2 | F5: =IFERROR(E5/$E$16,0) | G5: não iniciada | H5: 0 | I5: 0 | J5: =SUMIFS(Cotações!$K$2:$K$2,Cotações!$G$2:$G$2,$A5,Cotações!$C$2:$C$2,"<>mão de obra") | K5: =SUMIFS(Cotações!$K$2:$K$2,Cotações!$G$2:$G$2,$A5,Cotações!$C$2:$C$2,"mão de obra") | L5: =J5+K5 | M5: =IF(L5=0,"",D5-L5) | N5: vigas (portão, testada 7,30, balanço sacada) + escada aberta
A6: 4 | B6: Paredes: Monolev (estrutural) + divisórias Lightwall | C6: 110000 | D6: 156000 | E6: =(C6+D6)/2 | F6: =IFERROR(E6/$E$16,0) | G6: não iniciada | H6: 0 | I6: 0 | J6: =SUMIFS(Cotações!$K$2:$K$2,Cotações!$G$2:$G$2,$A6,Cotações!$C$2:$C$2,"<>mão de obra") | K6: =SUMIFS(Cotações!$K$2:$K$2,Cotações!$G$2:$G$2,$A6,Cotações!$C$2:$C$2,"mão de obra") | L6: =J6+K6 | M6: =IF(L6=0,"",D6-L6) | N6: Monolev ~340 m² líq. (perímetro/estruturais + térreo) · divisórias internas do superior ~80 m² em Lightwall 2P 90 mm (conceito mezanino: só o perímetro segura o telhado) · juntas dissimilares Monolev↔Lightwall c/ tela + basecoat
A7: 5 | B7: Lajes de PISO (superior + sacada + técnica) | C7: 19000 | D7: 26000 | E7: =(C7+D7)/2 | F7: =IFERROR(E7/$E$16,0) | G7: não iniciada | H7: 0 | I7: 0 | J7: =SUMIFS(Cotações!$K$2:$K$2,Cotações!$G$2:$G$2,$A7,Cotações!$C$2:$C$2,"<>mão de obra") | K7: =SUMIFS(Cotações!$K$2:$K$2,Cotações!$G$2:$G$2,$A7,Cotações!$C$2:$C$2,"mão de obra") | L7: =J7+K7 | M7: =IF(L7=0,"",D7-L7) | N7: 86 m² vigotas + EPS + capa — apenas pisos estruturais; NÃO há laje de forro
A8: 6 | B8: Cobertura + lanternim | C8: 40000 | D8: 60000 | E8: =(C8+D8)/2 | F8: =IFERROR(E8/$E$16,0) | G8: não iniciada | H8: 0 | I8: 0 | J8: =SUMIFS(Cotações!$K$2:$K$2,Cotações!$G$2:$G$2,$A8,Cotações!$C$2:$C$2,"<>mão de obra") | K8: =SUMIFS(Cotações!$K$2:$K$2,Cotações!$G$2:$G$2,$A8,Cotações!$C$2:$C$2,"mão de obra") | L8: =J8+K8 | M8: =IF(L8=0,"",D8-L8) | N8: estrutura, telha sanduíche, vidro/básculas, rufos e calhas
A9: 7 | B9: Esquadrias e vidros | C9: 58000 | D9: 90000 | E9: =(C9+D9)/2 | F9: =IFERROR(E9/$E$16,0) | G9: não iniciada | H9: 0 | I9: 0 | J9: =SUMIFS(Cotações!$K$2:$K$2,Cotações!$G$2:$G$2,$A9,Cotações!$C$2:$C$2,"<>mão de obra") | K9: =SUMIFS(Cotações!$K$2:$K$2,Cotações!$G$2:$G$2,$A9,Cotações!$C$2:$C$2,"mão de obra") | L9: =J9+K9 | M9: =IF(L9=0,"",D9-L9) | N9: inclui janelão espelhado, porta balcão 3,5 m e da suíte 7 m
A10: 8 | B10: Hidráulica + água quente + prep. PV | C10: 33000 | D10: 52000 | E10: =(C10+D10)/2 | F10: =IFERROR(E10/$E$16,0) | G10: não iniciada | H10: 0 | I10: 0 | J10: =SUMIFS(Cotações!$K$2:$K$2,Cotações!$G$2:$G$2,$A10,Cotações!$C$2:$C$2,"<>mão de obra") | K10: =SUMIFS(Cotações!$K$2:$K$2,Cotações!$G$2:$G$2,$A10,Cotações!$C$2:$C$2,"mão de obra") | L10: =J10+K10 | M10: =IF(L10=0,"",D10-L10) | N10: bomba de calor, boiler 400 L, pressurização, PEX/manifold
A11: 9 | B11: Elétrica + automação + rede | C11: 45000 | D11: 70000 | E11: =(C11+D11)/2 | F11: =IFERROR(E11/$E$16,0) | G11: não iniciada | H11: 0 | I11: 0 | J11: =SUMIFS(Cotações!$K$2:$K$2,Cotações!$G$2:$G$2,$A11,Cotações!$C$2:$C$2,"<>mão de obra") | K11: =SUMIFS(Cotações!$K$2:$K$2,Cotações!$G$2:$G$2,$A11,Cotações!$C$2:$C$2,"mão de obra") | L11: =J11+K11 | M11: =IF(L11=0,"",D11-L11) | N11: trifásico, Home Assistant, câmeras, 220 V nos cômodos
A12: 10 | B12: Climatização | C12: 18000 | D12: 28000 | E12: =(C12+D12)/2 | F12: =IFERROR(E12/$E$16,0) | G12: não iniciada | H12: 0 | I12: 0 | J12: =SUMIFS(Cotações!$K$2:$K$2,Cotações!$G$2:$G$2,$A12,Cotações!$C$2:$C$2,"<>mão de obra") | K12: =SUMIFS(Cotações!$K$2:$K$2,Cotações!$G$2:$G$2,$A12,Cotações!$C$2:$C$2,"mão de obra") | L12: =J12+K12 | M12: =IF(L12=0,"",D12-L12) | N12: multi-split tri + split sala + destratificador, R-32
A13: 11 | B13: Acabamentos resinados (sem porcelanato) | C13: 48000 | D13: 82000 | E13: =(C13+D13)/2 | F13: =IFERROR(E13/$E$16,0) | G13: não iniciada | H13: 0 | I13: 0 | J13: =SUMIFS(Cotações!$K$2:$K$2,Cotações!$G$2:$G$2,$A13,Cotações!$C$2:$C$2,"<>mão de obra") | K13: =SUMIFS(Cotações!$K$2:$K$2,Cotações!$G$2:$G$2,$A13,Cotações!$C$2:$C$2,"mão de obra") | L13: =J13+K13 | M13: =IF(L13=0,"",D13-L13) | N13: resinados + carpete de pedra + microcimento · forro gesso+EPS ~47 m² (quartos/copa/banheiros/corredor) · forro de MADEIRA ~45 m² acompanhando o telhado (mezanino + vão duplo)
A14: 12 | B14: Gourmet (Invisacook, bancada, churrasqueira) | C14: 20000 | D14: 33000 | E14: =(C14+D14)/2 | F14: =IFERROR(E14/$E$16,0) | G14: não iniciada | H14: 0 | I14: 0 | J14: =SUMIFS(Cotações!$K$2:$K$2,Cotações!$G$2:$G$2,$A14,Cotações!$C$2:$C$2,"<>mão de obra") | K14: =SUMIFS(Cotações!$K$2:$K$2,Cotações!$G$2:$G$2,$A14,Cotações!$C$2:$C$2,"mão de obra") | L14: =J14+K14 | M14: =IF(L14=0,"",D14-L14) | N14: porcelanato sinterizado, cooktop gás externo
A15: 13 | B15: Canteiro, limpeza e imprevistos (~8%) | C15: 30000 | D15: 50000 | E15: =(C15+D15)/2 | F15: =IFERROR(E15/$E$16,0) | G15: não iniciada | H15: 0 | I15: 0 | J15: =SUMIFS(Cotações!$K$2:$K$2,Cotações!$G$2:$G$2,$A15,Cotações!$C$2:$C$2,"<>mão de obra") | K15: =SUMIFS(Cotações!$K$2:$K$2,Cotações!$G$2:$G$2,$A15,Cotações!$C$2:$C$2,"mão de obra") | L15: =J15+K15 | M15: =IF(L15=0,"",D15-L15) | N15: reserva técnica
B16: TOTAL | C16: =SUM(C3:C15) | D16: =SUM(D3:D15) | E16: =SUM(E3:E15) | F16: 100% | I16: =SUM(I3:I15) | J16: =SUM(J3:J15) | K16: =SUM(K3:K15) | L16: =SUM(L3:L15)

Sheet Itens
A1: CATÁLOGO DE ITENS COTÁVEIS
A2: Base do formulário de cotação do site. Quantidades = memória de cálculo do projeto.
A3: ID | B3: Categoria | C3: Tipo | D3: Etapa | E3: Item | F3: Especificação | G3: Un | H3: Qtde | I3: Nº cotações | J3: Melhor preço unit. | K3: Melhor fornecedor | L3: Melhor total | M3: Observação
A4: IT001 | B4: Geral / Estrutura | C4: material | D4: 4 | E4: Painéis EPS (Monolev) — parede líquida ESTRUTURAL (perímetro + estruturais do térreo) | G4: m² | H4: 320 | I4: =COUNTIFS(Cotações!$E$2:$E$2,$A4) | J4: =IF(I4=0,"—",_xlfn.MINIFS(Cotações!$J$2:$J$2,Cotações!$E$2:$E$2,$A4)) | K4: =IF(I4=0,"—",IFERROR(INDEX(Cotações!$H$2:$H$2,MATCH(1,INDEX((Cotações!$E$2:$E$2=$A4)*(Cotações!$J$2:$J$2=J4),0),0)),"")) | L4: =IF(I4=0,"—",IFERROR(J4*H4,"")) | M4: divisórias não estruturais (lavabo e banheiro do térreo + todo o superior) migradas p/ Lightwall
A5: IT002 | B5: Geral / Estrutura | C5: material | D5: 4 | E5: Argamassa projetada estrutural (2 faces) | G5: m² | H5: 640 | I5: =COUNTIFS(Cotações!$E$2:$E$2,$A5) | J5: =IF(I5=0,"—",_xlfn.MINIFS(Cotações!$J$2:$J$2,Cotações!$E$2:$E$2,$A5)) | K5: =IF(I5=0,"—",IFERROR(INDEX(Cotações!$H$2:$H$2,MATCH(1,INDEX((Cotações!$E$2:$E$2=$A5)*(Cotações!$J$2:$J$2=J5),0),0)),"")) | L5: =IF(I5=0,"—",IFERROR(J5*H5,"")) | M5: 2 faces × 320 m²
A6: IT003 | B6: Geral / Estrutura | C6: material | D6: 4 | E6: Telas de reforço e acessórios de canto — verba complementar | F6: telas de vão (diagonais sobre cantos de janela/porta), reforços de ancoragem e arremates não cobertos pela cantoneira | G6: vb | H6: 1 | I6: =COUNTIFS(Cotações!$E$2:$E$2,$A6) | J6: =IF(I6=0,"—",_xlfn.MINIFS(Cotações!$J$2:$J$2,Cotações!$E$2:$E$2,$A6)) | K6: =IF(I6=0,"—",IFERROR(INDEX(Cotações!$H$2:$H$2,MATCH(1,INDEX((Cotações!$E$2:$E$2=$A6)*(Cotações!$J$2:$J$2=J6),0),0)),"")) | L6: =IF(I6=0,"—",IFERROR(J6*H6,"")) | M6: cotar no pacote do painel · a cantoneira de canto está no item próprio (ver Cantoneira PVC c/ tela)
A7: IT004 | B7: Geral / Estrutura | C7: material | D7: 5 | E7: Laje vigotas + EPS — PISO do superior + técnica (estrutural) | G7: m² | H7: 70 | I7: =COUNTIFS(Cotações!$E$2:$E$2,$A7) | J7: =IF(I7=0,"—",_xlfn.MINIFS(Cotações!$J$2:$J$2,Cotações!$E$2:$E$2,$A7)) | K7: =IF(I7=0,"—",IFERROR(INDEX(Cotações!$H$2:$H$2,MATCH(1,INDEX((Cotações!$E$2:$E$2=$A7)*(Cotações!$J$2:$J$2=J7),0),0)),"")) | L7: =IF(I7=0,"—",IFERROR(J7*H7,"")) | M7: inclui capa de concreto · é o piso, não forro
A8: IT005 | B8: Geral / Estrutura | C8: material | D8: 2 | E8: Radier (fundação) | G8: m² | H8: 103 | I8: =COUNTIFS(Cotações!$E$2:$E$2,$A8) | J8: =IF(I8=0,"—",_xlfn.MINIFS(Cotações!$J$2:$J$2,Cotações!$E$2:$E$2,$A8)) | K8: =IF(I8=0,"—",IFERROR(INDEX(Cotações!$H$2:$H$2,MATCH(1,INDEX((Cotações!$E$2:$E$2=$A8)*(Cotações!$J$2:$J$2=J8),0),0)),"")) | L8: =IF(I8=0,"—",IFERROR(J8*H8,"")) | M8: casa 95 + extensão garagem 8
A9: IT006 | B9: Geral / Estrutura | C9: material | D9: 3 | E9: Vigas metálicas: testada da laje (7,30 livre, SEM pilar) + balanço da sacada 2,50 | G9: vb | H9: 1 | I9: =COUNTIFS(Cotações!$E$2:$E$2,$A9) | J9: =IF(I9=0,"—",_xlfn.MINIFS(Cotações!$J$2:$J$2,Cotações!$E$2:$E$2,$A9)) | K9: =IF(I9=0,"—",IFERROR(INDEX(Cotações!$H$2:$H$2,MATCH(1,INDEX((Cotações!$E$2:$E$2=$A9)*(Cotações!$J$2:$J$2=J9),0),0)),"")) | L9: =IF(I9=0,"—",IFERROR(J9*H9,"")) | M9: perfis I + engaste sob a suíte — projeto estrutural
A10: IT007 | B10: Geral / Estrutura | C10: material | D10: 6 | E10: Estrutura metálica da cobertura — 3 treliças galvanizadas a fogo + terças/contrav. Z275 | F10: 3 treliças banzos paralelos h=0,40 @3,25 (vão 7,30, degrau triangulado no lanternim): banzos tubo 50×50×2,00 · diagonais 30×30×2,00 · ~72 kg/un · terças Ue100×50×17×2,00 4 linhas @1,33/0,98 · contrav. Ø12 + esticador · vigotas Ue150 @1,25 sobre serviço · ~0,95-1,15 t | G10: m² | H10: 95 | I10: =COUNTIFS(Cotações!$E$2:$E$2,$A10) | J10: =IF(I10=0,"—",_xlfn.MINIFS(Cotações!$J$2:$J$2,Cotações!$E$2:$E$2,$A10)) | K10: =IF(I10=0,"—",IFERROR(INDEX(Cotações!$H$2:$H$2,MATCH(1,INDEX((Cotações!$E$2:$E$2=$A10)*(Cotações!$J$2:$J$2=J10),0),0)),"")) | L10: =IF(I10=0,"—",IFERROR(J10*H10,"")) | M10: treliças soldadas em fábrica e galvanizadas a fogo INTEIRAS, parafusadas em obra (tubos c/ furo de dreno) · oitões NO/SE apoiam direto na parede · plenum de 0,40 entre banzos p/ ventilador, luminárias e linhas do split · ver F-07/F-08/F-09
A11: IT008 | B11: Geral / Estrutura | C11: material | D11: 6 | E11: Telha sanduíche EPS | G11: m² | H11: 100 | I11: =COUNTIFS(Cotações!$E$2:$E$2,$A11) | J11: =IF(I11=0,"—",_xlfn.MINIFS(Cotações!$J$2:$J$2,Cotações!$E$2:$E$2,$A11)) | K11: =IF(I11=0,"—",IFERROR(INDEX(Cotações!$H$2:$H$2,MATCH(1,INDEX((Cotações!$E$2:$E$2=$A11)*(Cotações!$J$2:$J$2=J11),0),0)),"")) | L11: =IF(I11=0,"—",IFERROR(J11*H11,"")) | M11: não cobre a faixa de luz (8,20 × 1,20 descoberta) · cobre serviço/técnica (4,00 × 1,20)
A12: IT009 | B12: Geral / Estrutura | C12: material | D12: 6 | E12: Lanternim — vidro laminado/policarbonato + básculas | G12: m² | H12: 12 | I12: =COUNTIFS(Cotações!$E$2:$E$2,$A12) | J12: =IF(I12=0,"—",_xlfn.MINIFS(Cotações!$J$2:$J$2,Cotações!$E$2:$E$2,$A12)) | K12: =IF(I12=0,"—",IFERROR(INDEX(Cotações!$H$2:$H$2,MATCH(1,INDEX((Cotações!$E$2:$E$2=$A12)*(Cotações!$J$2:$J$2=J12),0),0)),"")) | L12: =IF(I12=0,"—",IFERROR(J12*H12,"")) | M12: 13 m × 0,90
A13: IT010 | B13: Geral / Estrutura | C13: material | D13: 6 | E13: Rufos e arremates — oitões, chaminé e lanternim | F13: chapa galvanizada #24 (0,65 mm) ou alumínio · dobra ≥150 mm na parede e ≥200 mm sobre a telha, com pingadeira | G13: vb | H13: 1 | I13: =COUNTIFS(Cotações!$E$2:$E$2,$A13) | J13: =IF(I13=0,"—",_xlfn.MINIFS(Cotações!$J$2:$J$2,Cotações!$E$2:$E$2,$A13)) | K13: =IF(I13=0,"—",IFERROR(INDEX(Cotações!$H$2:$H$2,MATCH(1,INDEX((Cotações!$E$2:$E$2=$A13)*(Cotações!$J$2:$J$2=J13),0),0)),"")) | L13: =IF(I13=0,"—",IFERROR(J13*H13,"")) | M13: ponto crítico de estanqueidade · lanternim tem rufo de topo E de base (ver F-09) · calhas em item próprio
A14: IT011 | B14: Geral / Estrutura | C14: material | D14: 3 | E14: Guarda-corpos (mezanino, corredor, escada) | G14: m | H14: 14 | I14: =COUNTIFS(Cotações!$E$2:$E$2,$A14) | J14: =IF(I14=0,"—",_xlfn.MINIFS(Cotações!$J$2:$J$2,Cotações!$E$2:$E$2,$A14)) | K14: =IF(I14=0,"—",IFERROR(INDEX(Cotações!$H$2:$H$2,MATCH(1,INDEX((Cotações!$E$2:$E$2=$A14)*(Cotações!$J$2:$J$2=J14),0),0)),"")) | L14: =IF(I14=0,"—",IFERROR(J14*H14,"")) | M14: metálico/vidro — definir
A15: IT012 | B15: Geral / Estrutura | C15: material | D15: 3 | E15: Escada metálica aberta (fachada norte) | G15: vb | H15: 1 | I15: =COUNTIFS(Cotações!$E$2:$E$2,$A15) | J15: =IF(I15=0,"—",_xlfn.MINIFS(Cotações!$J$2:$J$2,Cotações!$E$2:$E$2,$A15)) | K15: =IF(I15=0,"—",IFERROR(INDEX(Cotações!$H$2:$H$2,MATCH(1,INDEX((Cotações!$E$2:$E$2=$A15)*(Cotações!$J$2:$J$2=J15),0),0)),"")) | L15: =IF(I15=0,"—",IFERROR(J15*H15,"")) | M15: estrutura + degraus
A16: IT013 | B16: Geral / Estrutura | C16: material | D16: 7 | E16: Esquadrias (janelas, porta balcão, portas) | G16: vb | H16: 1 | I16: =COUNTIFS(Cotações!$E$2:$E$2,$A16) | J16: =IF(I16=0,"—",_xlfn.MINIFS(Cotações!$J$2:$J$2,Cotações!$E$2:$E$2,$A16)) | K16: =IF(I16=0,"—",IFERROR(INDEX(Cotações!$H$2:$H$2,MATCH(1,INDEX((Cotações!$E$2:$E$2=$A16)*(Cotações!$J$2:$J$2=J16),0),0)),"")) | L16: =IF(I16=0,"—",IFERROR(J16*H16,"")) | M16: detalhar por vão
A17: IT014 | B17: Geral / Estrutura | C17: material | D17: 9 | E17: Elétrica + automação — ver aba Elétrica | G17: vb | H17: 1 | I17: =COUNTIFS(Cotações!$E$2:$E$2,$A17) | J17: =IF(I17=0,"—",_xlfn.MINIFS(Cotações!$J$2:$J$2,Cotações!$E$2:$E$2,$A17)) | K17: =IF(I17=0,"—",IFERROR(INDEX(Cotações!$H$2:$H$2,MATCH(1,INDEX((Cotações!$E$2:$E$2=$A17)*(Cotações!$J$2:$J$2=J17),0),0)),"")) | L17: =IF(I17=0,"—",IFERROR(J17*H17,"")) | M17: quantitativo detalhado na aba própria
A18: IT015 | B18: Geral / Estrutura | C18: material | D18: 11 | E18: Impermeabilizações (banheiros, laje técnica) | G18: vb | H18: 1 | I18: =COUNTIFS(Cotações!$E$2:$E$2,$A18) | J18: =IF(I18=0,"—",_xlfn.MINIFS(Cotações!$J$2:$J$2,Cotações!$E$2:$E$2,$A18)) | K18: =IF(I18=0,"—",IFERROR(INDEX(Cotações!$H$2:$H$2,MATCH(1,INDEX((Cotações!$E$2:$E$2=$A18)*(Cotações!$J$2:$J$2=J18),0),0)),"")) | L18: =IF(I18=0,"—",IFERROR(J18*H18,"")) | M18: CRÍTICO: banheiros sem box drenam pela camada de pedra — impermeabilizar TODO o piso c/ caimento ao ralo oculto
A19: IT016 | B19: Geral / Estrutura | C19: material | D19: 8 | E19: Hidráulica completa + preparação PV | G19: vb | H19: 1 | I19: =COUNTIFS(Cotações!$E$2:$E$2,$A19) | J19: =IF(I19=0,"—",_xlfn.MINIFS(Cotações!$J$2:$J$2,Cotações!$E$2:$E$2,$A19)) | K19: =IF(I19=0,"—",IFERROR(INDEX(Cotações!$H$2:$H$2,MATCH(1,INDEX((Cotações!$E$2:$E$2=$A19)*(Cotações!$J$2:$J$2=J19),0),0)),"")) | L19: =IF(I19=0,"—",IFERROR(J19*H19,"")) | M19: ver aba Hidráulica
A20: IT017 | B20: Geral / Estrutura | C20: serviço | D20: 1 | E20: Sondagem SPT (2–3 furos) | F20: insumo do projeto de fundação (radier) | G20: vb | H20: 1 | I20: =COUNTIFS(Cotações!$E$2:$E$2,$A20) | J20: =IF(I20=0,"—",_xlfn.MINIFS(Cotações!$J$2:$J$2,Cotações!$E$2:$E$2,$A20)) | K20: =IF(I20=0,"—",IFERROR(INDEX(Cotações!$H$2:$H$2,MATCH(1,INDEX((Cotações!$E$2:$E$2=$A20)*(Cotações!$J$2:$J$2=J20),0),0)),"")) | L20: =IF(I20=0,"—",IFERROR(J20*H20,"")) | M20: fazer ANTES do projeto de fundação
A21: IT018 | B21: Geral / Estrutura | C21: material | D21: 10 | E21: Climatização — ver aba Climatização | G21: vb | H21: 1 | I21: =COUNTIFS(Cotações!$E$2:$E$2,$A21) | J21: =IF(I21=0,"—",_xlfn.MINIFS(Cotações!$J$2:$J$2,Cotações!$E$2:$E$2,$A21)) | K21: =IF(I21=0,"—",IFERROR(INDEX(Cotações!$H$2:$H$2,MATCH(1,INDEX((Cotações!$E$2:$E$2=$A21)*(Cotações!$J$2:$J$2=J21),0),0)),"")) | L21: =IF(I21=0,"—",IFERROR(J21*H21,"")) | M21: infra elétrica dos 5 pontos já na aba Elétrica
A22: IT019 | B22: Geral / Estrutura | C22: material | D22: 5 | E22: Laje da sacada/varanda (vigotas + EPS + capa) | G22: m² | H22: 18 | I22: =COUNTIFS(Cotações!$E$2:$E$2,$A22) | J22: =IF(I22=0,"—",_xlfn.MINIFS(Cotações!$J$2:$J$2,Cotações!$E$2:$E$2,$A22)) | K22: =IF(I22=0,"—",IFERROR(INDEX(Cotações!$H$2:$H$2,MATCH(1,INDEX((Cotações!$E$2:$E$2=$A22)*(Cotações!$J$2:$J$2=J22),0),0)),"")) | L22: =IF(I22=0,"—",IFERROR(J22*H22,"")) | M22: sobre vigas metálicas em balanço
A23: IT020 | B23: Geral / Estrutura | C23: material | D23: 11 | E23: Impermeabilização do piso da extensão (sobre varanda aberta) | G23: m² | H23: 18 | I23: =COUNTIFS(Cotações!$E$2:$E$2,$A23) | J23: =IF(I23=0,"—",_xlfn.MINIFS(Cotações!$J$2:$J$2,Cotações!$E$2:$E$2,$A23)) | K23: =IF(I23=0,"—",IFERROR(INDEX(Cotações!$H$2:$H$2,MATCH(1,INDEX((Cotações!$E$2:$E$2=$A23)*(Cotações!$J$2:$J$2=J23),0),0)),"")) | L23: =IF(I23=0,"—",IFERROR(J23*H23,"")) | M23: varanda gourmet abaixo
A24: IT021 | B24: Geral / Estrutura | C24: material | D24: 7 | E24: Mureta + envidraçamento da extensão da suíte (vidro até o forro) | G24: m² | H24: 21 | I24: =COUNTIFS(Cotações!$E$2:$E$2,$A24) | J24: =IF(I24=0,"—",_xlfn.MINIFS(Cotações!$J$2:$J$2,Cotações!$E$2:$E$2,$A24)) | K24: =IF(I24=0,"—",IFERROR(INDEX(Cotações!$H$2:$H$2,MATCH(1,INDEX((Cotações!$E$2:$E$2=$A24)*(Cotações!$J$2:$J$2=J24),0),0)),"")) | L24: =IF(I24=0,"—",IFERROR(J24*H24,"")) | M24: perímetro 12,3 m × ~1,7 m de vidro sobre mureta
A25: IT022 | B25: Geral / Estrutura | C25: material | D25: 11 | E25: Forro da extensão da suíte (esconde o V do telhado) | G25: m² | H25: 18 | I25: =COUNTIFS(Cotações!$E$2:$E$2,$A25) | J25: =IF(I25=0,"—",_xlfn.MINIFS(Cotações!$J$2:$J$2,Cotações!$E$2:$E$2,$A25)) | K25: =IF(I25=0,"—",IFERROR(INDEX(Cotações!$H$2:$H$2,MATCH(1,INDEX((Cotações!$E$2:$E$2=$A25)*(Cotações!$J$2:$J$2=J25),0),0)),"")) | L25: =IF(I25=0,"—",IFERROR(J25*H25,"")) | M25: gesso/PVC sobre a extensão · suíte integrada, sem porta
A26: IT023 | B26: Geral / Estrutura | C26: material | D26: 12 | E26: Churrasqueira + chaminé acima da cobertura | G26: vb | H26: 1 | I26: =COUNTIFS(Cotações!$E$2:$E$2,$A26) | J26: =IF(I26=0,"—",_xlfn.MINIFS(Cotações!$J$2:$J$2,Cotações!$E$2:$E$2,$A26)) | K26: =IF(I26=0,"—",IFERROR(INDEX(Cotações!$H$2:$H$2,MATCH(1,INDEX((Cotações!$E$2:$E$2=$A26)*(Cotações!$J$2:$J$2=J26),0),0)),"")) | L26: =IF(I26=0,"—",IFERROR(J26*H26,"")) | M26: canto leste da varanda
A27: IT024 | B27: Geral / Estrutura | C27: material | D27: 12 | E27: Cooktop a gás externo + abrigo P13 + kit instalação | G27: vb | H27: 1 | I27: =COUNTIFS(Cotações!$E$2:$E$2,$A27) | J27: =IF(I27=0,"—",_xlfn.MINIFS(Cotações!$J$2:$J$2,Cotações!$E$2:$E$2,$A27)) | K27: =IF(I27=0,"—",IFERROR(INDEX(Cotações!$H$2:$H$2,MATCH(1,INDEX((Cotações!$E$2:$E$2=$A27)*(Cotações!$J$2:$J$2=J27),0),0)),"")) | L27: =IF(I27=0,"—",IFERROR(J27*H27,"")) | M27: redundância — gás só na varanda
A28: IT025 | B28: Geral / Estrutura | C28: material | D28: 12 | E28: Bancada ilha: porcelanato sinterizado 12 mm + rebaixo italiano | G28: m² | H28: 5 | I28: =COUNTIFS(Cotações!$E$2:$E$2,$A28) | J28: =IF(I28=0,"—",_xlfn.MINIFS(Cotações!$J$2:$J$2,Cotações!$E$2:$E$2,$A28)) | K28: =IF(I28=0,"—",IFERROR(INDEX(Cotações!$H$2:$H$2,MATCH(1,INDEX((Cotações!$E$2:$E$2=$A28)*(Cotações!$J$2:$J$2=J28),0),0)),"")) | L28: =IF(I28=0,"—",IFERROR(J28*H28,"")) | M28: quartzo/resina NÃO compatível c/ Invisacook
A29: IT026 | B29: Geral / Estrutura | C29: material | D29: 12 | E29: Invisacook 4 zonas + acessórios (mantas, indicadores) | G29: un | H29: 1 | I29: =COUNTIFS(Cotações!$E$2:$E$2,$A29) | J29: =IF(I29=0,"—",_xlfn.MINIFS(Cotações!$J$2:$J$2,Cotações!$E$2:$E$2,$A29)) | K29: =IF(I29=0,"—",IFERROR(INDEX(Cotações!$H$2:$H$2,MATCH(1,INDEX((Cotações!$E$2:$E$2=$A29)*(Cotações!$J$2:$J$2=J29),0),0)),"")) | L29: =IF(I29=0,"—",IFERROR(J29*H29,"")) | M29: circuito 40 A na aba Elétrica
A30: IT027 | B30: Geral / Estrutura | C30: material | D30: 7 | E30: Janelão vertical fachada noroeste (vidro laminado) + película espelhada | F30: parede da escada · 3,20 × 4,70 m · peitoril 1,00 · caixilho estruturado | G30: m² | H30: 15 | I30: =COUNTIFS(Cotações!$E$2:$E$2,$A30) | J30: =IF(I30=0,"—",_xlfn.MINIFS(Cotações!$J$2:$J$2,Cotações!$E$2:$E$2,$A30)) | K30: =IF(I30=0,"—",IFERROR(INDEX(Cotações!$H$2:$H$2,MATCH(1,INDEX((Cotações!$E$2:$E$2=$A30)*(Cotações!$J$2:$J$2=J30),0),0)),"")) | L30: =IF(I30=0,"—",IFERROR(J30*H30,"")) | M30: CORRIGIDO: largura alinhada à planta F-02 (era 2,2 m no catálogo e 2,4 m na elevação — a planta sempre mostrou 3,20 m, cobrindo todo o lance da escada) · película espelhada só no trecho do piso superior; térreo com vidro transparente
A31: IT028 | B31: Hidráulica | C31: material | D31: 8 | E31: Tubo PEX 20 mm (água quente) | F31: PEX-A c/ barreira anti-O₂ | G31: m | H31: 75 | I31: =COUNTIFS(Cotações!$E$2:$E$2,$A31) | J31: =IF(I31=0,"—",_xlfn.MINIFS(Cotações!$J$2:$J$2,Cotações!$E$2:$E$2,$A31)) | K31: =IF(I31=0,"—",IFERROR(INDEX(Cotações!$H$2:$H$2,MATCH(1,INDEX((Cotações!$E$2:$E$2=$A31)*(Cotações!$J$2:$J$2=J31),0),0)),"")) | L31: =IF(I31=0,"—",IFERROR(J31*H31,"")) | M31: ramais quentes + anel de recirculação
A32: IT029 | B32: Hidráulica | C32: material | D32: 8 | E32: Isolamento térmico p/ PEX 20 mm | F32: polietileno exp. 10 mm parede | G32: m | H32: 75 | I32: =COUNTIFS(Cotações!$E$2:$E$2,$A32) | J32: =IF(I32=0,"—",_xlfn.MINIFS(Cotações!$J$2:$J$2,Cotações!$E$2:$E$2,$A32)) | K32: =IF(I32=0,"—",IFERROR(INDEX(Cotações!$H$2:$H$2,MATCH(1,INDEX((Cotações!$E$2:$E$2=$A32)*(Cotações!$J$2:$J$2=J32),0),0)),"")) | L32: =IF(I32=0,"—",IFERROR(J32*H32,"")) | M32: obrigatório em 100% da linha quente
A33: IT030 | B33: Hidráulica | C33: material | D33: 8 | E33: Tubo PEX 16/20 mm (água fria) | F33: PEX-A | G33: m | H33: 100 | I33: =COUNTIFS(Cotações!$E$2:$E$2,$A33) | J33: =IF(I33=0,"—",_xlfn.MINIFS(Cotações!$J$2:$J$2,Cotações!$E$2:$E$2,$A33)) | K33: =IF(I33=0,"—",IFERROR(INDEX(Cotações!$H$2:$H$2,MATCH(1,INDEX((Cotações!$E$2:$E$2=$A33)*(Cotações!$J$2:$J$2=J33),0),0)),"")) | L33: =IF(I33=0,"—",IFERROR(J33*H33,"")) | M33: ramais frios ponto a ponto (manifold)
A34: IT031 | B34: Hidráulica | C34: material | D34: 8 | E34: Tubo PPR PN25 32 mm | F34: barrilete caixa→pressurizador→manifolds/boiler | G34: m | H34: 18 | I34: =COUNTIFS(Cotações!$E$2:$E$2,$A34) | J34: =IF(I34=0,"—",_xlfn.MINIFS(Cotações!$J$2:$J$2,Cotações!$E$2:$E$2,$A34)) | K34: =IF(I34=0,"—",IFERROR(INDEX(Cotações!$H$2:$H$2,MATCH(1,INDEX((Cotações!$E$2:$E$2=$A34)*(Cotações!$J$2:$J$2=J34),0),0)),"")) | L34: =IF(I34=0,"—",IFERROR(J34*H34,""))
A35: IT032 | B35: Hidráulica | C35: material | D35: 8 | E35: Tubo PPR PN25 28 mm | F35: circuito bomba de calor ↔ boiler | G35: m | H35: 8 | I35: =COUNTIFS(Cotações!$E$2:$E$2,$A35) | J35: =IF(I35=0,"—",_xlfn.MINIFS(Cotações!$J$2:$J$2,Cotações!$E$2:$E$2,$A35)) | K35: =IF(I35=0,"—",IFERROR(INDEX(Cotações!$H$2:$H$2,MATCH(1,INDEX((Cotações!$E$2:$E$2=$A35)*(Cotações!$J$2:$J$2=J35),0),0)),"")) | L35: =IF(I35=0,"—",IFERROR(J35*H35,"")) | M35: isolar também
A36: IT033 | B36: Hidráulica | C36: material | D36: 8 | E36: Isolamento p/ PPR 28/32 mm | F36: polietileno exp. | G36: m | H36: 26 | I36: =COUNTIFS(Cotações!$E$2:$E$2,$A36) | J36: =IF(I36=0,"—",_xlfn.MINIFS(Cotações!$J$2:$J$2,Cotações!$E$2:$E$2,$A36)) | K36: =IF(I36=0,"—",IFERROR(INDEX(Cotações!$H$2:$H$2,MATCH(1,INDEX((Cotações!$E$2:$E$2=$A36)*(Cotações!$J$2:$J$2=J36),0),0)),"")) | L36: =IF(I36=0,"—",IFERROR(J36*H36,""))
A37: IT034 | B37: Hidráulica | C37: material | D37: 8 | E37: Tubo PVC soldável 25 mm | F37: alimentação da caixa + torneiras jardim/garagem | G37: m | H37: 20 | I37: =COUNTIFS(Cotações!$E$2:$E$2,$A37) | J37: =IF(I37=0,"—",_xlfn.MINIFS(Cotações!$J$2:$J$2,Cotações!$E$2:$E$2,$A37)) | K37: =IF(I37=0,"—",IFERROR(INDEX(Cotações!$H$2:$H$2,MATCH(1,INDEX((Cotações!$E$2:$E$2=$A37)*(Cotações!$J$2:$J$2=J37),0),0)),"")) | L37: =IF(I37=0,"—",IFERROR(J37*H37,""))
A38: IT035 | B38: Hidráulica | C38: material | D38: 8 | E38: Tubo PVC esgoto 100 mm | F38: prumadas de vasos + ventilação | G38: m | H38: 22 | I38: =COUNTIFS(Cotações!$E$2:$E$2,$A38) | J38: =IF(I38=0,"—",_xlfn.MINIFS(Cotações!$J$2:$J$2,Cotações!$E$2:$E$2,$A38)) | K38: =IF(I38=0,"—",IFERROR(INDEX(Cotações!$H$2:$H$2,MATCH(1,INDEX((Cotações!$E$2:$E$2=$A38)*(Cotações!$J$2:$J$2=J38),0),0)),"")) | L38: =IF(I38=0,"—",IFERROR(J38*H38,"")) | M38: 2 prumadas + coletor
A39: IT036 | B39: Hidráulica | C39: material | D39: 8 | E39: Tubo PVC esgoto 50 mm | F39: chuveiros, ralos, tanque, máquina | G39: m | H39: 25 | I39: =COUNTIFS(Cotações!$E$2:$E$2,$A39) | J39: =IF(I39=0,"—",_xlfn.MINIFS(Cotações!$J$2:$J$2,Cotações!$E$2:$E$2,$A39)) | K39: =IF(I39=0,"—",IFERROR(INDEX(Cotações!$H$2:$H$2,MATCH(1,INDEX((Cotações!$E$2:$E$2=$A39)*(Cotações!$J$2:$J$2=J39),0),0)),"")) | L39: =IF(I39=0,"—",IFERROR(J39*H39,""))
A40: IT037 | B40: Hidráulica | C40: material | D40: 8 | E40: Tubo PVC esgoto 40 mm | F40: lavatórios, pias, dreno boiler/copa | G40: m | H40: 15 | I40: =COUNTIFS(Cotações!$E$2:$E$2,$A40) | J40: =IF(I40=0,"—",_xlfn.MINIFS(Cotações!$J$2:$J$2,Cotações!$E$2:$E$2,$A40)) | K40: =IF(I40=0,"—",IFERROR(INDEX(Cotações!$H$2:$H$2,MATCH(1,INDEX((Cotações!$E$2:$E$2=$A40)*(Cotações!$J$2:$J$2=J40),0),0)),"")) | L40: =IF(I40=0,"—",IFERROR(J40*H40,""))
A41: IT038 | B41: Hidráulica | C41: material | D41: 8 | E41: Tubo PVC pluvial 88 mm | F41: condutores das calhas | G41: m | H41: 12 | I41: =COUNTIFS(Cotações!$E$2:$E$2,$A41) | J41: =IF(I41=0,"—",_xlfn.MINIFS(Cotações!$J$2:$J$2,Cotações!$E$2:$E$2,$A41)) | K41: =IF(I41=0,"—",IFERROR(INDEX(Cotações!$H$2:$H$2,MATCH(1,INDEX((Cotações!$E$2:$E$2=$A41)*(Cotações!$J$2:$J$2=J41),0),0)),"")) | L41: =IF(I41=0,"—",IFERROR(J41*H41,"")) | M41: 2 descidas
A42: IT039 | B42: Hidráulica | C42: material | D42: 8 | E42: Conexões esgoto/pluvial (kit) | F42: joelhos, tês, junções, terminais vent. | G42: un | H42: 45 | I42: =COUNTIFS(Cotações!$E$2:$E$2,$A42) | J42: =IF(I42=0,"—",_xlfn.MINIFS(Cotações!$J$2:$J$2,Cotações!$E$2:$E$2,$A42)) | K42: =IF(I42=0,"—",IFERROR(INDEX(Cotações!$H$2:$H$2,MATCH(1,INDEX((Cotações!$E$2:$E$2=$A42)*(Cotações!$J$2:$J$2=J42),0),0)),"")) | L42: =IF(I42=0,"—",IFERROR(J42*H42,""))
A43: IT040 | B43: Hidráulica | C43: material | D43: 8 | E43: Caixa sifonada 150 mm | G43: un | H43: 5 | I43: =COUNTIFS(Cotações!$E$2:$E$2,$A43) | J43: =IF(I43=0,"—",_xlfn.MINIFS(Cotações!$J$2:$J$2,Cotações!$E$2:$E$2,$A43)) | K43: =IF(I43=0,"—",IFERROR(INDEX(Cotações!$H$2:$H$2,MATCH(1,INDEX((Cotações!$E$2:$E$2=$A43)*(Cotações!$J$2:$J$2=J43),0),0)),"")) | L43: =IF(I43=0,"—",IFERROR(J43*H43,"")) | M43: banheiros, lavanderia, copa
A44: IT041 | B44: Hidráulica | C44: material | D44: 8 | E44: Ralo linear oculto (inox) | F44: banheiros sem box — sob carpete de pedra drenante | G44: un | H44: 3 | I44: =COUNTIFS(Cotações!$E$2:$E$2,$A44) | J44: =IF(I44=0,"—",_xlfn.MINIFS(Cotações!$J$2:$J$2,Cotações!$E$2:$E$2,$A44)) | K44: =IF(I44=0,"—",IFERROR(INDEX(Cotações!$H$2:$H$2,MATCH(1,INDEX((Cotações!$E$2:$E$2=$A44)*(Cotações!$J$2:$J$2=J44),0),0)),"")) | L44: =IF(I44=0,"—",IFERROR(J44*H44,"")) | M44: suíte, banheiro do quarto e banheiro do térreo · o lavabo do térreo não leva ralo linear
A45: IT042 | B45: Hidráulica | C45: material | D45: 8 | E45: Caixa de gordura | F45: cozinha | G45: un | H45: 1 | I45: =COUNTIFS(Cotações!$E$2:$E$2,$A45) | J45: =IF(I45=0,"—",_xlfn.MINIFS(Cotações!$J$2:$J$2,Cotações!$E$2:$E$2,$A45)) | K45: =IF(I45=0,"—",IFERROR(INDEX(Cotações!$H$2:$H$2,MATCH(1,INDEX((Cotações!$E$2:$E$2=$A45)*(Cotações!$J$2:$J$2=J45),0),0)),"")) | L45: =IF(I45=0,"—",IFERROR(J45*H45,""))
A46: IT043 | B46: Hidráulica | C46: material | D46: 8 | E46: Caixa de inspeção esgoto | G46: un | H46: 2 | I46: =COUNTIFS(Cotações!$E$2:$E$2,$A46) | J46: =IF(I46=0,"—",_xlfn.MINIFS(Cotações!$J$2:$J$2,Cotações!$E$2:$E$2,$A46)) | K46: =IF(I46=0,"—",IFERROR(INDEX(Cotações!$H$2:$H$2,MATCH(1,INDEX((Cotações!$E$2:$E$2=$A46)*(Cotações!$J$2:$J$2=J46),0),0)),"")) | L46: =IF(I46=0,"—",IFERROR(J46*H46,"")) | M46: quintal → rede do condomínio
A47: IT044 | B47: Hidráulica | C47: material | D47: 8 | E47: Manifold água fria c/ registros | F47: 12 saídas, latão/inox | G47: un | H47: 1 | I47: =COUNTIFS(Cotações!$E$2:$E$2,$A47) | J47: =IF(I47=0,"—",_xlfn.MINIFS(Cotações!$J$2:$J$2,Cotações!$E$2:$E$2,$A47)) | K47: =IF(I47=0,"—",IFERROR(INDEX(Cotações!$H$2:$H$2,MATCH(1,INDEX((Cotações!$E$2:$E$2=$A47)*(Cotações!$J$2:$J$2=J47),0),0)),"")) | L47: =IF(I47=0,"—",IFERROR(J47*H47,"")) | M47: na área técnica
A48: IT045 | B48: Hidráulica | C48: material | D48: 8 | E48: Manifold água quente c/ registros | F48: 8 saídas | G48: un | H48: 1 | I48: =COUNTIFS(Cotações!$E$2:$E$2,$A48) | J48: =IF(I48=0,"—",_xlfn.MINIFS(Cotações!$J$2:$J$2,Cotações!$E$2:$E$2,$A48)) | K48: =IF(I48=0,"—",IFERROR(INDEX(Cotações!$H$2:$H$2,MATCH(1,INDEX((Cotações!$E$2:$E$2=$A48)*(Cotações!$J$2:$J$2=J48),0),0)),"")) | L48: =IF(I48=0,"—",IFERROR(J48*H48,""))
A49: IT046 | B49: Hidráulica | C49: material | D49: 8 | E49: Conexões PEX | F49: joelhos, tês, adaptadores de engate | G49: un | H49: 60 | I49: =COUNTIFS(Cotações!$E$2:$E$2,$A49) | J49: =IF(I49=0,"—",_xlfn.MINIFS(Cotações!$J$2:$J$2,Cotações!$E$2:$E$2,$A49)) | K49: =IF(I49=0,"—",IFERROR(INDEX(Cotações!$H$2:$H$2,MATCH(1,INDEX((Cotações!$E$2:$E$2=$A49)*(Cotações!$J$2:$J$2=J49),0),0)),"")) | L49: =IF(I49=0,"—",IFERROR(J49*H49,""))
A50: IT047 | B50: Hidráulica | C50: material | D50: 8 | E50: Conexões PPR diversas | F50: joelhos, tês, luvas, uniões | G50: un | H50: 35 | I50: =COUNTIFS(Cotações!$E$2:$E$2,$A50) | J50: =IF(I50=0,"—",_xlfn.MINIFS(Cotações!$J$2:$J$2,Cotações!$E$2:$E$2,$A50)) | K50: =IF(I50=0,"—",IFERROR(INDEX(Cotações!$H$2:$H$2,MATCH(1,INDEX((Cotações!$E$2:$E$2=$A50)*(Cotações!$J$2:$J$2=J50),0),0)),"")) | L50: =IF(I50=0,"—",IFERROR(J50*H50,""))
A51: IT048 | B51: Hidráulica | C51: material | D51: 8 | E51: Registro de esfera metálico 3/4" | G51: un | H51: 12 | I51: =COUNTIFS(Cotações!$E$2:$E$2,$A51) | J51: =IF(I51=0,"—",_xlfn.MINIFS(Cotações!$J$2:$J$2,Cotações!$E$2:$E$2,$A51)) | K51: =IF(I51=0,"—",IFERROR(INDEX(Cotações!$H$2:$H$2,MATCH(1,INDEX((Cotações!$E$2:$E$2=$A51)*(Cotações!$J$2:$J$2=J51),0),0)),"")) | L51: =IF(I51=0,"—",IFERROR(J51*H51,"")) | M51: setorização por ambiente
A52: IT049 | B52: Hidráulica | C52: material | D52: 8 | E52: Válvula de retenção | G52: un | H52: 3 | I52: =COUNTIFS(Cotações!$E$2:$E$2,$A52) | J52: =IF(I52=0,"—",_xlfn.MINIFS(Cotações!$J$2:$J$2,Cotações!$E$2:$E$2,$A52)) | K52: =IF(I52=0,"—",IFERROR(INDEX(Cotações!$H$2:$H$2,MATCH(1,INDEX((Cotações!$E$2:$E$2=$A52)*(Cotações!$J$2:$J$2=J52),0),0)),"")) | L52: =IF(I52=0,"—",IFERROR(J52*H52,"")) | M52: entrada caixa, fria, quente
A53: IT050 | B53: Hidráulica | C53: material | D53: 8 | E53: Misturadora termostática central | F53: saída do boiler, limite ~50 °C | G53: un | H53: 1 | I53: =COUNTIFS(Cotações!$E$2:$E$2,$A53) | J53: =IF(I53=0,"—",_xlfn.MINIFS(Cotações!$J$2:$J$2,Cotações!$E$2:$E$2,$A53)) | K53: =IF(I53=0,"—",IFERROR(INDEX(Cotações!$H$2:$H$2,MATCH(1,INDEX((Cotações!$E$2:$E$2=$A53)*(Cotações!$J$2:$J$2=J53),0),0)),"")) | L53: =IF(I53=0,"—",IFERROR(J53*H53,"")) | M53: anti-escaldo
A54: IT051 | B54: Hidráulica | C54: material | D54: 8 | E54: Válvula de alívio P&T + dreno conduzido | G54: un | H54: 1 | I54: =COUNTIFS(Cotações!$E$2:$E$2,$A54) | J54: =IF(I54=0,"—",_xlfn.MINIFS(Cotações!$J$2:$J$2,Cotações!$E$2:$E$2,$A54)) | K54: =IF(I54=0,"—",IFERROR(INDEX(Cotações!$H$2:$H$2,MATCH(1,INDEX((Cotações!$E$2:$E$2=$A54)*(Cotações!$J$2:$J$2=J54),0),0)),"")) | L54: =IF(I54=0,"—",IFERROR(J54*H54,"")) | M54: obrigatória no boiler
A55: IT052 | B55: Hidráulica | C55: material | D55: 8 | E55: Vaso de expansão água quente 18–24 L | G55: un | H55: 1 | I55: =COUNTIFS(Cotações!$E$2:$E$2,$A55) | J55: =IF(I55=0,"—",_xlfn.MINIFS(Cotações!$J$2:$J$2,Cotações!$E$2:$E$2,$A55)) | K55: =IF(I55=0,"—",IFERROR(INDEX(Cotações!$H$2:$H$2,MATCH(1,INDEX((Cotações!$E$2:$E$2=$A55)*(Cotações!$J$2:$J$2=J55),0),0)),"")) | L55: =IF(I55=0,"—",IFERROR(J55*H55,""))
A56: IT053 | B56: Hidráulica | C56: material | D56: 8 | E56: Filtro de entrada (cavalete) | G56: un | H56: 1 | I56: =COUNTIFS(Cotações!$E$2:$E$2,$A56) | J56: =IF(I56=0,"—",_xlfn.MINIFS(Cotações!$J$2:$J$2,Cotações!$E$2:$E$2,$A56)) | K56: =IF(I56=0,"—",IFERROR(INDEX(Cotações!$H$2:$H$2,MATCH(1,INDEX((Cotações!$E$2:$E$2=$A56)*(Cotações!$J$2:$J$2=J56),0),0)),"")) | L56: =IF(I56=0,"—",IFERROR(J56*H56,""))
A57: IT054 | B57: Hidráulica | C57: material | D57: 8 | E57: Bomba de calor AQS | F57: ~5 kW térmico, COP ≥ 3,5, Wi-Fi | G57: un | H57: 1 | I57: =COUNTIFS(Cotações!$E$2:$E$2,$A57) | J57: =IF(I57=0,"—",_xlfn.MINIFS(Cotações!$J$2:$J$2,Cotações!$E$2:$E$2,$A57)) | K57: =IF(I57=0,"—",IFERROR(INDEX(Cotações!$H$2:$H$2,MATCH(1,INDEX((Cotações!$E$2:$E$2=$A57)*(Cotações!$J$2:$J$2=J57),0),0)),"")) | L57: =IF(I57=0,"—",IFERROR(J57*H57,"")) | M57: unidade externa no poço de luz
A58: IT055 | B58: Hidráulica | C58: material | D58: 8 | E58: Boiler inox alta pressão 400 L | F58: c/ resistência de apoio e anodo | G58: un | H58: 1 | I58: =COUNTIFS(Cotações!$E$2:$E$2,$A58) | J58: =IF(I58=0,"—",_xlfn.MINIFS(Cotações!$J$2:$J$2,Cotações!$E$2:$E$2,$A58)) | K58: =IF(I58=0,"—",IFERROR(INDEX(Cotações!$H$2:$H$2,MATCH(1,INDEX((Cotações!$E$2:$E$2=$A58)*(Cotações!$J$2:$J$2=J58),0),0)),"")) | L58: =IF(I58=0,"—",IFERROR(J58*H58,"")) | M58: na área técnica, c/ 60 cm livres
A59: IT056 | B59: Hidráulica | C59: material | D59: 8 | E59: Sistema de pressurização | F59: bomba + vaso de expansão (ou pressurizador de linha) | G59: un | H59: 1 | I59: =COUNTIFS(Cotações!$E$2:$E$2,$A59) | J59: =IF(I59=0,"—",_xlfn.MINIFS(Cotações!$J$2:$J$2,Cotações!$E$2:$E$2,$A59)) | K59: =IF(I59=0,"—",IFERROR(INDEX(Cotações!$H$2:$H$2,MATCH(1,INDEX((Cotações!$E$2:$E$2=$A59)*(Cotações!$J$2:$J$2=J59),0),0)),"")) | L59: =IF(I59=0,"—",IFERROR(J59*H59,"")) | M59: antes da bifurcação fria/quente
A60: IT057 | B60: Hidráulica | C60: material | D60: 8 | E60: Bomba de recirculação c/ acionamento por demanda | F60: + timer/relé p/ automação | G60: un | H60: 1 | I60: =COUNTIFS(Cotações!$E$2:$E$2,$A60) | J60: =IF(I60=0,"—",_xlfn.MINIFS(Cotações!$J$2:$J$2,Cotações!$E$2:$E$2,$A60)) | K60: =IF(I60=0,"—",IFERROR(INDEX(Cotações!$H$2:$H$2,MATCH(1,INDEX((Cotações!$E$2:$E$2=$A60)*(Cotações!$J$2:$J$2=J60),0),0)),"")) | L60: =IF(I60=0,"—",IFERROR(J60*H60,"")) | M60: retorno da suíte
A61: IT058 | B61: Hidráulica | C61: material | D61: 8 | E61: Caixa d'água 1.000 L | F61: c/ bóia, extravasor e limpeza | G61: un | H61: 1 | I61: =COUNTIFS(Cotações!$E$2:$E$2,$A61) | J61: =IF(I61=0,"—",_xlfn.MINIFS(Cotações!$J$2:$J$2,Cotações!$E$2:$E$2,$A61)) | K61: =IF(I61=0,"—",IFERROR(INDEX(Cotações!$H$2:$H$2,MATCH(1,INDEX((Cotações!$E$2:$E$2=$A61)*(Cotações!$J$2:$J$2=J61),0),0)),"")) | L61: =IF(I61=0,"—",IFERROR(J61*H61,""))
A62: IT059 | B62: Hidráulica | C62: material | D62: 8 | E62: Purificador cozinha + ponto bebedouro copa | G62: un | H62: 2 | I62: =COUNTIFS(Cotações!$E$2:$E$2,$A62) | J62: =IF(I62=0,"—",_xlfn.MINIFS(Cotações!$J$2:$J$2,Cotações!$E$2:$E$2,$A62)) | K62: =IF(I62=0,"—",IFERROR(INDEX(Cotações!$H$2:$H$2,MATCH(1,INDEX((Cotações!$E$2:$E$2=$A62)*(Cotações!$J$2:$J$2=J62),0),0)),"")) | L62: =IF(I62=0,"—",IFERROR(J62*H62,"")) | M62: copa: prever dreno
A63: IT060 | B63: Hidráulica | C63: material | D63: 8 | E63: Eletroduto 32 mm telhado → área técnica | F63: c/ caixas de passagem e arame-guia | G63: m | H63: 10 | I63: =COUNTIFS(Cotações!$E$2:$E$2,$A63) | J63: =IF(I63=0,"—",_xlfn.MINIFS(Cotações!$J$2:$J$2,Cotações!$E$2:$E$2,$A63)) | K63: =IF(I63=0,"—",IFERROR(INDEX(Cotações!$H$2:$H$2,MATCH(1,INDEX((Cotações!$E$2:$E$2=$A63)*(Cotações!$J$2:$J$2=J63),0),0)),"")) | L63: =IF(I63=0,"—",IFERROR(J63*H63,"")) | M63: desce pelo shaft da técnica
A64: IT061 | B64: Hidráulica | C64: material | D64: 8 | E64: QDC c/ reserva p/ inversor | F64: espaço + disjuntor bidirecional futuro | G64: vb | H64: 1 | I64: =COUNTIFS(Cotações!$E$2:$E$2,$A64) | J64: =IF(I64=0,"—",_xlfn.MINIFS(Cotações!$J$2:$J$2,Cotações!$E$2:$E$2,$A64)) | K64: =IF(I64=0,"—",IFERROR(INDEX(Cotações!$H$2:$H$2,MATCH(1,INDEX((Cotações!$E$2:$E$2=$A64)*(Cotações!$J$2:$J$2=J64),0),0)),"")) | L64: =IF(I64=0,"—",IFERROR(J64*H64,""))
A65: IT062 | B65: Hidráulica | C65: material | D65: 8 | E65: Aterramento reforçado / SPDA prep. | F65: hastes + cabo de descida | G65: vb | H65: 1 | I65: =COUNTIFS(Cotações!$E$2:$E$2,$A65) | J65: =IF(I65=0,"—",_xlfn.MINIFS(Cotações!$J$2:$J$2,Cotações!$E$2:$E$2,$A65)) | K65: =IF(I65=0,"—",IFERROR(INDEX(Cotações!$H$2:$H$2,MATCH(1,INDEX((Cotações!$E$2:$E$2=$A65)*(Cotações!$J$2:$J$2=J65),0),0)),"")) | L65: =IF(I65=0,"—",IFERROR(J65*H65,"")) | M65: estrutura metálica do telhado exige
A66: IT063 | B66: Hidráulica | C66: material | D66: 8 | E66: Reforço de fixação na água oeste | F66: pontos de ancoragem previstos na estrutura | G66: vb | H66: 1 | I66: =COUNTIFS(Cotações!$E$2:$E$2,$A66) | J66: =IF(I66=0,"—",_xlfn.MINIFS(Cotações!$J$2:$J$2,Cotações!$E$2:$E$2,$A66)) | K66: =IF(I66=0,"—",IFERROR(INDEX(Cotações!$H$2:$H$2,MATCH(1,INDEX((Cotações!$E$2:$E$2=$A66)*(Cotações!$J$2:$J$2=J66),0),0)),"")) | L66: =IF(I66=0,"—",IFERROR(J66*H66,"")) | M66: painéis futuros na água alta
A67: IT064 | B67: Elétrica + Automação | C67: material | D67: 9 | E67: Padrão de entrada trifásico | F67: poste/caixa padrão Enel SP, 3F+N, disjuntor geral 40–50 A | G67: vb | H67: 1 | I67: =COUNTIFS(Cotações!$E$2:$E$2,$A67) | J67: =IF(I67=0,"—",_xlfn.MINIFS(Cotações!$J$2:$J$2,Cotações!$E$2:$E$2,$A67)) | K67: =IF(I67=0,"—",IFERROR(INDEX(Cotações!$H$2:$H$2,MATCH(1,INDEX((Cotações!$E$2:$E$2=$A67)*(Cotações!$J$2:$J$2=J67),0),0)),"")) | L67: =IF(I67=0,"—",IFERROR(J67*H67,"")) | M67: dá 220 V fase-fase e 127 V fase-neutro
A68: IT065 | B68: Elétrica + Automação | C68: material | D68: 9 | E68: Alimentador medidor → QDC | F68: cabo 16 mm² (4 vias) + eletroduto 40 mm | G68: m | H68: 18 | I68: =COUNTIFS(Cotações!$E$2:$E$2,$A68) | J68: =IF(I68=0,"—",_xlfn.MINIFS(Cotações!$J$2:$J$2,Cotações!$E$2:$E$2,$A68)) | K68: =IF(I68=0,"—",IFERROR(INDEX(Cotações!$H$2:$H$2,MATCH(1,INDEX((Cotações!$E$2:$E$2=$A68)*(Cotações!$J$2:$J$2=J68),0),0)),"")) | L68: =IF(I68=0,"—",IFERROR(J68*H68,""))
A69: IT066 | B69: Elétrica + Automação | C69: material | D69: 9 | E69: QDC 32 circuitos c/ barramento trifásico | F69: embutir na área técnica | G69: un | H69: 1 | I69: =COUNTIFS(Cotações!$E$2:$E$2,$A69) | J69: =IF(I69=0,"—",_xlfn.MINIFS(Cotações!$J$2:$J$2,Cotações!$E$2:$E$2,$A69)) | K69: =IF(I69=0,"—",IFERROR(INDEX(Cotações!$H$2:$H$2,MATCH(1,INDEX((Cotações!$E$2:$E$2=$A69)*(Cotações!$J$2:$J$2=J69),0),0)),"")) | L69: =IF(I69=0,"—",IFERROR(J69*H69,"")) | M69: reserva p/ inversor PV já prevista
A70: IT067 | B70: Elétrica + Automação | C70: material | D70: 9 | E70: Disjuntores DIN (mono e bifásicos) | F70: curvas B/C conforme circuito | G70: un | H70: 26 | I70: =COUNTIFS(Cotações!$E$2:$E$2,$A70) | J70: =IF(I70=0,"—",_xlfn.MINIFS(Cotações!$J$2:$J$2,Cotações!$E$2:$E$2,$A70)) | K70: =IF(I70=0,"—",IFERROR(INDEX(Cotações!$H$2:$H$2,MATCH(1,INDEX((Cotações!$E$2:$E$2=$A70)*(Cotações!$J$2:$J$2=J70),0),0)),"")) | L70: =IF(I70=0,"—",IFERROR(J70*H70,""))
A71: IT068 | B71: Elétrica + Automação | C71: material | D71: 9 | E71: IDR / DR 30 mA | F71: banheiros, áreas molhadas, externas, cozinha | G71: un | H71: 4 | I71: =COUNTIFS(Cotações!$E$2:$E$2,$A71) | J71: =IF(I71=0,"—",_xlfn.MINIFS(Cotações!$J$2:$J$2,Cotações!$E$2:$E$2,$A71)) | K71: =IF(I71=0,"—",IFERROR(INDEX(Cotações!$H$2:$H$2,MATCH(1,INDEX((Cotações!$E$2:$E$2=$A71)*(Cotações!$J$2:$J$2=J71),0),0)),"")) | L71: =IF(I71=0,"—",IFERROR(J71*H71,"")) | M71: obrigatório NBR 5410
A72: IT069 | B72: Elétrica + Automação | C72: material | D72: 9 | E72: DPS classe II (F+F+F+N) | F72: no QDC | G72: un | H72: 4 | I72: =COUNTIFS(Cotações!$E$2:$E$2,$A72) | J72: =IF(I72=0,"—",_xlfn.MINIFS(Cotações!$J$2:$J$2,Cotações!$E$2:$E$2,$A72)) | K72: =IF(I72=0,"—",IFERROR(INDEX(Cotações!$H$2:$H$2,MATCH(1,INDEX((Cotações!$E$2:$E$2=$A72)*(Cotações!$J$2:$J$2=J72),0),0)),"")) | L72: =IF(I72=0,"—",IFERROR(J72*H72,"")) | M72: telhado metálico: essencial
A73: IT070 | B73: Elétrica + Automação | C73: material | D73: 9 | E73: Aterramento | F73: 3 hastes + cabo cobre nu 16 mm² + caixa inspeção | G73: vb | H73: 1 | I73: =COUNTIFS(Cotações!$E$2:$E$2,$A73) | J73: =IF(I73=0,"—",_xlfn.MINIFS(Cotações!$J$2:$J$2,Cotações!$E$2:$E$2,$A73)) | K73: =IF(I73=0,"—",IFERROR(INDEX(Cotações!$H$2:$H$2,MATCH(1,INDEX((Cotações!$E$2:$E$2=$A73)*(Cotações!$J$2:$J$2=J73),0),0)),"")) | L73: =IF(I73=0,"—",IFERROR(J73*H73,"")) | M73: integra c/ SPDA da cobertura
A74: IT071 | B74: Elétrica + Automação | C74: material | D74: 9 | E74: Eletroduto corrugado reforçado 25 mm | F74: sulcos no EPS c/ soprador térmico | G74: m | H74: 260 | I74: =COUNTIFS(Cotações!$E$2:$E$2,$A74) | J74: =IF(I74=0,"—",_xlfn.MINIFS(Cotações!$J$2:$J$2,Cotações!$E$2:$E$2,$A74)) | K74: =IF(I74=0,"—",IFERROR(INDEX(Cotações!$H$2:$H$2,MATCH(1,INDEX((Cotações!$E$2:$E$2=$A74)*(Cotações!$J$2:$J$2=J74),0),0)),"")) | L74: =IF(I74=0,"—",IFERROR(J74*H74,""))
A75: IT072 | B75: Elétrica + Automação | C75: material | D75: 9 | E75: Eletroduto corrugado 32 mm | F75: circuitos 220 V, AC e troncos | G75: m | H75: 50 | I75: =COUNTIFS(Cotações!$E$2:$E$2,$A75) | J75: =IF(I75=0,"—",_xlfn.MINIFS(Cotações!$J$2:$J$2,Cotações!$E$2:$E$2,$A75)) | K75: =IF(I75=0,"—",IFERROR(INDEX(Cotações!$H$2:$H$2,MATCH(1,INDEX((Cotações!$E$2:$E$2=$A75)*(Cotações!$J$2:$J$2=J75),0),0)),"")) | L75: =IF(I75=0,"—",IFERROR(J75*H75,""))
A76: IT073 | B76: Elétrica + Automação | C76: material | D76: 9 | E76: Caixa 4×2 (tomadas/interruptores) | G76: un | H76: 75 | I76: =COUNTIFS(Cotações!$E$2:$E$2,$A76) | J76: =IF(I76=0,"—",_xlfn.MINIFS(Cotações!$J$2:$J$2,Cotações!$E$2:$E$2,$A76)) | K76: =IF(I76=0,"—",IFERROR(INDEX(Cotações!$H$2:$H$2,MATCH(1,INDEX((Cotações!$E$2:$E$2=$A76)*(Cotações!$J$2:$J$2=J76),0),0)),"")) | L76: =IF(I76=0,"—",IFERROR(J76*H76,""))
A77: IT074 | B77: Elétrica + Automação | C77: material | D77: 9 | E77: Caixa 4×4 | F77: pontos duplos, automação, rede | G77: un | H77: 18 | I77: =COUNTIFS(Cotações!$E$2:$E$2,$A77) | J77: =IF(I77=0,"—",_xlfn.MINIFS(Cotações!$J$2:$J$2,Cotações!$E$2:$E$2,$A77)) | K77: =IF(I77=0,"—",IFERROR(INDEX(Cotações!$H$2:$H$2,MATCH(1,INDEX((Cotações!$E$2:$E$2=$A77)*(Cotações!$J$2:$J$2=J77),0),0)),"")) | L77: =IF(I77=0,"—",IFERROR(J77*H77,"")) | M77: interruptores smart pedem folga
A78: IT075 | B78: Elétrica + Automação | C78: material | D78: 9 | E78: Caixa octogonal/teto | F78: pontos de luz | G78: un | H78: 26 | I78: =COUNTIFS(Cotações!$E$2:$E$2,$A78) | J78: =IF(I78=0,"—",_xlfn.MINIFS(Cotações!$J$2:$J$2,Cotações!$E$2:$E$2,$A78)) | K78: =IF(I78=0,"—",IFERROR(INDEX(Cotações!$H$2:$H$2,MATCH(1,INDEX((Cotações!$E$2:$E$2=$A78)*(Cotações!$J$2:$J$2=J78),0),0)),"")) | L78: =IF(I78=0,"—",IFERROR(J78*H78,""))
A79: IT076 | B79: Elétrica + Automação | C79: material | D79: 9 | E79: Quadro de passagem / shaft técnica | F79: organização das descidas | G79: un | H79: 2 | I79: =COUNTIFS(Cotações!$E$2:$E$2,$A79) | J79: =IF(I79=0,"—",_xlfn.MINIFS(Cotações!$J$2:$J$2,Cotações!$E$2:$E$2,$A79)) | K79: =IF(I79=0,"—",IFERROR(INDEX(Cotações!$H$2:$H$2,MATCH(1,INDEX((Cotações!$E$2:$E$2=$A79)*(Cotações!$J$2:$J$2=J79),0),0)),"")) | L79: =IF(I79=0,"—",IFERROR(J79*H79,""))
A80: IT077 | B80: Elétrica + Automação | C80: material | D80: 9 | E80: Cabo flexível 1,5 mm² | F80: iluminação | G80: m | H80: 280 | I80: =COUNTIFS(Cotações!$E$2:$E$2,$A80) | J80: =IF(I80=0,"—",_xlfn.MINIFS(Cotações!$J$2:$J$2,Cotações!$E$2:$E$2,$A80)) | K80: =IF(I80=0,"—",IFERROR(INDEX(Cotações!$H$2:$H$2,MATCH(1,INDEX((Cotações!$E$2:$E$2=$A80)*(Cotações!$J$2:$J$2=J80),0),0)),"")) | L80: =IF(I80=0,"—",IFERROR(J80*H80,""))
A81: IT078 | B81: Elétrica + Automação | C81: material | D81: 9 | E81: Cabo flexível 2,5 mm² | F81: tomadas de uso geral 127 V | G81: m | H81: 420 | I81: =COUNTIFS(Cotações!$E$2:$E$2,$A81) | J81: =IF(I81=0,"—",_xlfn.MINIFS(Cotações!$J$2:$J$2,Cotações!$E$2:$E$2,$A81)) | K81: =IF(I81=0,"—",IFERROR(INDEX(Cotações!$H$2:$H$2,MATCH(1,INDEX((Cotações!$E$2:$E$2=$A81)*(Cotações!$J$2:$J$2=J81),0),0)),"")) | L81: =IF(I81=0,"—",IFERROR(J81*H81,""))
A82: IT079 | B82: Elétrica + Automação | C82: material | D82: 9 | E82: Cabo flexível 4,0 mm² | F82: tomadas 220 V + circuitos AC | G82: m | H82: 140 | I82: =COUNTIFS(Cotações!$E$2:$E$2,$A82) | J82: =IF(I82=0,"—",_xlfn.MINIFS(Cotações!$J$2:$J$2,Cotações!$E$2:$E$2,$A82)) | K82: =IF(I82=0,"—",IFERROR(INDEX(Cotações!$H$2:$H$2,MATCH(1,INDEX((Cotações!$E$2:$E$2=$A82)*(Cotações!$J$2:$J$2=J82),0),0)),"")) | L82: =IF(I82=0,"—",IFERROR(J82*H82,""))
A83: IT080 | B83: Elétrica + Automação | C83: material | D83: 9 | E83: Cabo flexível 6,0 mm² | F83: cooktop indução, bomba de calor, forno | G83: m | H83: 60 | I83: =COUNTIFS(Cotações!$E$2:$E$2,$A83) | J83: =IF(I83=0,"—",_xlfn.MINIFS(Cotações!$J$2:$J$2,Cotações!$E$2:$E$2,$A83)) | K83: =IF(I83=0,"—",IFERROR(INDEX(Cotações!$H$2:$H$2,MATCH(1,INDEX((Cotações!$E$2:$E$2=$A83)*(Cotações!$J$2:$J$2=J83),0),0)),"")) | L83: =IF(I83=0,"—",IFERROR(J83*H83,"")) | M83: todos 220 V dedicados
A84: IT081 | B84: Elétrica + Automação | C84: material | D84: 9 | E84: Cabo PP / bitolas especiais | F84: pressurizador, recirculadora, portão | G84: m | H84: 30 | I84: =COUNTIFS(Cotações!$E$2:$E$2,$A84) | J84: =IF(I84=0,"—",_xlfn.MINIFS(Cotações!$J$2:$J$2,Cotações!$E$2:$E$2,$A84)) | K84: =IF(I84=0,"—",IFERROR(INDEX(Cotações!$H$2:$H$2,MATCH(1,INDEX((Cotações!$E$2:$E$2=$A84)*(Cotações!$J$2:$J$2=J84),0),0)),"")) | L84: =IF(I84=0,"—",IFERROR(J84*H84,""))
A85: IT082 | B85: Elétrica + Automação | C85: material | D85: 9 | E85: Tomadas 2P+T 10 A — 127 V | F85: linha a definir | G85: un | H85: 42 | I85: =COUNTIFS(Cotações!$E$2:$E$2,$A85) | J85: =IF(I85=0,"—",_xlfn.MINIFS(Cotações!$J$2:$J$2,Cotações!$E$2:$E$2,$A85)) | K85: =IF(I85=0,"—",IFERROR(INDEX(Cotações!$H$2:$H$2,MATCH(1,INDEX((Cotações!$E$2:$E$2=$A85)*(Cotações!$J$2:$J$2=J85),0),0)),"")) | L85: =IF(I85=0,"—",IFERROR(J85*H85,""))
A86: IT083 | B86: Elétrica + Automação | C86: material | D86: 9 | E86: Tomadas 2P+T 20 A — 220 V | F86: identificadas (cor/etiqueta vermelha) | G86: un | H86: 16 | I86: =COUNTIFS(Cotações!$E$2:$E$2,$A86) | J86: =IF(I86=0,"—",_xlfn.MINIFS(Cotações!$J$2:$J$2,Cotações!$E$2:$E$2,$A86)) | K86: =IF(I86=0,"—",IFERROR(INDEX(Cotações!$H$2:$H$2,MATCH(1,INDEX((Cotações!$E$2:$E$2=$A86)*(Cotações!$J$2:$J$2=J86),0),0)),"")) | L86: =IF(I86=0,"—",IFERROR(J86*H86,"")) | M86: 2 por cômodo em média
A87: IT084 | B87: Elétrica + Automação | C87: material | D87: 9 | E87: Pontos de luz (teto/arandela/pendente) | G87: un | H87: 26 | I87: =COUNTIFS(Cotações!$E$2:$E$2,$A87) | J87: =IF(I87=0,"—",_xlfn.MINIFS(Cotações!$J$2:$J$2,Cotações!$E$2:$E$2,$A87)) | K87: =IF(I87=0,"—",IFERROR(INDEX(Cotações!$H$2:$H$2,MATCH(1,INDEX((Cotações!$E$2:$E$2=$A87)*(Cotações!$J$2:$J$2=J87),0),0)),"")) | L87: =IF(I87=0,"—",IFERROR(J87*H87,"")) | M87: inclui pendentes do pé-direito duplo
A88: IT085 | B88: Elétrica + Automação | C88: material | D88: 9 | E88: Fita LED + perfil alumínio | F88: sancas, closet, copa, escada | G88: m | H88: 22 | I88: =COUNTIFS(Cotações!$E$2:$E$2,$A88) | J88: =IF(I88=0,"—",_xlfn.MINIFS(Cotações!$J$2:$J$2,Cotações!$E$2:$E$2,$A88)) | K88: =IF(I88=0,"—",IFERROR(INDEX(Cotações!$H$2:$H$2,MATCH(1,INDEX((Cotações!$E$2:$E$2=$A88)*(Cotações!$J$2:$J$2=J88),0),0)),"")) | L88: =IF(I88=0,"—",IFERROR(J88*H88,""))
A89: IT086 | B89: Elétrica + Automação | C89: material | D89: 9 | E89: Interruptores (bases p/ smart) | F89: ver seção 6 | G89: un | H89: 18 | I89: =COUNTIFS(Cotações!$E$2:$E$2,$A89) | J89: =IF(I89=0,"—",_xlfn.MINIFS(Cotações!$J$2:$J$2,Cotações!$E$2:$E$2,$A89)) | K89: =IF(I89=0,"—",IFERROR(INDEX(Cotações!$H$2:$H$2,MATCH(1,INDEX((Cotações!$E$2:$E$2=$A89)*(Cotações!$J$2:$J$2=J89),0),0)),"")) | L89: =IF(I89=0,"—",IFERROR(J89*H89,""))
A90: IT087 | B90: Elétrica + Automação | C90: material | D90: 9 | E90: Circuitos dedicados 220 V p/ AC | F90: ponto + dreno + tomada | G90: un | H90: 5 | I90: =COUNTIFS(Cotações!$E$2:$E$2,$A90) | J90: =IF(I90=0,"—",_xlfn.MINIFS(Cotações!$J$2:$J$2,Cotações!$E$2:$E$2,$A90)) | K90: =IF(I90=0,"—",IFERROR(INDEX(Cotações!$H$2:$H$2,MATCH(1,INDEX((Cotações!$E$2:$E$2=$A90)*(Cotações!$J$2:$J$2=J90),0),0)),"")) | L90: =IF(I90=0,"—",IFERROR(J90*H90,"")) | M90: infra pronta; aparelhos em outra sessão
A91: IT088 | B91: Elétrica + Automação | C91: material | D91: 9 | E91: Tomadas externas IP55 | F91: quintal, jardim, área de luz, garagem | G91: un | H91: 5 | I91: =COUNTIFS(Cotações!$E$2:$E$2,$A91) | J91: =IF(I91=0,"—",_xlfn.MINIFS(Cotações!$J$2:$J$2,Cotações!$E$2:$E$2,$A91)) | K91: =IF(I91=0,"—",IFERROR(INDEX(Cotações!$H$2:$H$2,MATCH(1,INDEX((Cotações!$E$2:$E$2=$A91)*(Cotações!$J$2:$J$2=J91),0),0)),"")) | L91: =IF(I91=0,"—",IFERROR(J91*H91,"")) | M91: em circuito c/ DR
A92: IT089 | B92: Elétrica + Automação | C92: material | D92: 9 | E92: Cabo CAT6 | F92: pontos fixos + câmeras + APs | G92: m | H92: 300 | I92: =COUNTIFS(Cotações!$E$2:$E$2,$A92) | J92: =IF(I92=0,"—",_xlfn.MINIFS(Cotações!$J$2:$J$2,Cotações!$E$2:$E$2,$A92)) | K92: =IF(I92=0,"—",IFERROR(INDEX(Cotações!$H$2:$H$2,MATCH(1,INDEX((Cotações!$E$2:$E$2=$A92)*(Cotações!$J$2:$J$2=J92),0),0)),"")) | L92: =IF(I92=0,"—",IFERROR(J92*H92,""))
A93: IT090 | B93: Elétrica + Automação | C93: material | D93: 9 | E93: Pontos de rede (RJ45 duplos) | F93: TVs, escritório/mezanino, copa, técnica | G93: un | H93: 10 | I93: =COUNTIFS(Cotações!$E$2:$E$2,$A93) | J93: =IF(I93=0,"—",_xlfn.MINIFS(Cotações!$J$2:$J$2,Cotações!$E$2:$E$2,$A93)) | K93: =IF(I93=0,"—",IFERROR(INDEX(Cotações!$H$2:$H$2,MATCH(1,INDEX((Cotações!$E$2:$E$2=$A93)*(Cotações!$J$2:$J$2=J93),0),0)),"")) | L93: =IF(I93=0,"—",IFERROR(J93*H93,""))
A94: IT091 | B94: Elétrica + Automação | C94: material | D94: 9 | E94: Rack 6U + patch panel + organizador | F94: na área técnica | G94: un | H94: 1 | I94: =COUNTIFS(Cotações!$E$2:$E$2,$A94) | J94: =IF(I94=0,"—",_xlfn.MINIFS(Cotações!$J$2:$J$2,Cotações!$E$2:$E$2,$A94)) | K94: =IF(I94=0,"—",IFERROR(INDEX(Cotações!$H$2:$H$2,MATCH(1,INDEX((Cotações!$E$2:$E$2=$A94)*(Cotações!$J$2:$J$2=J94),0),0)),"")) | L94: =IF(I94=0,"—",IFERROR(J94*H94,""))
A95: IT092 | B95: Elétrica + Automação | C95: material | D95: 9 | E95: Switch PoE 16 portas | G95: un | H95: 1 | I95: =COUNTIFS(Cotações!$E$2:$E$2,$A95) | J95: =IF(I95=0,"—",_xlfn.MINIFS(Cotações!$J$2:$J$2,Cotações!$E$2:$E$2,$A95)) | K95: =IF(I95=0,"—",IFERROR(INDEX(Cotações!$H$2:$H$2,MATCH(1,INDEX((Cotações!$E$2:$E$2=$A95)*(Cotações!$J$2:$J$2=J95),0),0)),"")) | L95: =IF(I95=0,"—",IFERROR(J95*H95,"")) | M95: alimenta câmeras e APs
A96: IT093 | B96: Elétrica + Automação | C96: material | D96: 9 | E96: Access points Wi-Fi 6 | F96: térreo + superior | G96: un | H96: 2 | I96: =COUNTIFS(Cotações!$E$2:$E$2,$A96) | J96: =IF(I96=0,"—",_xlfn.MINIFS(Cotações!$J$2:$J$2,Cotações!$E$2:$E$2,$A96)) | K96: =IF(I96=0,"—",IFERROR(INDEX(Cotações!$H$2:$H$2,MATCH(1,INDEX((Cotações!$E$2:$E$2=$A96)*(Cotações!$J$2:$J$2=J96),0),0)),"")) | L96: =IF(I96=0,"—",IFERROR(J96*H96,"")) | M96: EPS atenua pouco, 2 bastam
A97: IT094 | B97: Elétrica + Automação | C97: material | D97: 9 | E97: Câmeras IP PoE externas | F97: frente, viela, quintal, garagem | G97: un | H97: 4 | I97: =COUNTIFS(Cotações!$E$2:$E$2,$A97) | J97: =IF(I97=0,"—",_xlfn.MINIFS(Cotações!$J$2:$J$2,Cotações!$E$2:$E$2,$A97)) | K97: =IF(I97=0,"—",IFERROR(INDEX(Cotações!$H$2:$H$2,MATCH(1,INDEX((Cotações!$E$2:$E$2=$A97)*(Cotações!$J$2:$J$2=J97),0),0)),"")) | L97: =IF(I97=0,"—",IFERROR(J97*H97,""))
A98: IT095 | B98: Elétrica + Automação | C98: material | D98: 9 | E98: Videoporteiro IP | F98: sem muro: módulo na fachada/jardim | G98: un | H98: 1 | I98: =COUNTIFS(Cotações!$E$2:$E$2,$A98) | J98: =IF(I98=0,"—",_xlfn.MINIFS(Cotações!$J$2:$J$2,Cotações!$E$2:$E$2,$A98)) | K98: =IF(I98=0,"—",IFERROR(INDEX(Cotações!$H$2:$H$2,MATCH(1,INDEX((Cotações!$E$2:$E$2=$A98)*(Cotações!$J$2:$J$2=J98),0),0)),"")) | L98: =IF(I98=0,"—",IFERROR(J98*H98,""))
A99: IT096 | B99: Elétrica + Automação | C99: material | D99: 9 | E99: Fechadura eletrônica | F99: porta de entrada (garagem→sala) | G99: un | H99: 1 | I99: =COUNTIFS(Cotações!$E$2:$E$2,$A99) | J99: =IF(I99=0,"—",_xlfn.MINIFS(Cotações!$J$2:$J$2,Cotações!$E$2:$E$2,$A99)) | K99: =IF(I99=0,"—",IFERROR(INDEX(Cotações!$H$2:$H$2,MATCH(1,INDEX((Cotações!$E$2:$E$2=$A99)*(Cotações!$J$2:$J$2=J99),0),0)),"")) | L99: =IF(I99=0,"—",IFERROR(J99*H99,""))
A100: IT097 | B100: Elétrica + Automação | C100: material | D100: 9 | E100: Hub central (Home Assistant + coordenador Zigbee) | F100: mini PC ou appliance no rack | G100: un | H100: 1 | I100: =COUNTIFS(Cotações!$E$2:$E$2,$A100) | J100: =IF(I100=0,"—",_xlfn.MINIFS(Cotações!$J$2:$J$2,Cotações!$E$2:$E$2,$A100)) | K100: =IF(I100=0,"—",IFERROR(INDEX(Cotações!$H$2:$H$2,MATCH(1,INDEX((Cotações!$E$2:$E$2=$A100)*(Cotações!$J$2:$J$2=J100),0),0)),"")) | L100: =IF(I100=0,"—",IFERROR(J100*H100,"")) | M100: controle local, sem dependência de nuvem
...

Sheet Cotações
A1: ID | B1: Data | C1: Tipo | D1: Categoria | E1: Item ID | F1: Item | G1: Etapa | H1: Fornecedor / empreiteiro | I1: Qtde | J1: Preço unit. | K1: Total | L1: Melhor? | M1: Observação
A3: Nenhuma cotação lançada ainda — use o formulário do site.

Sheet Comparativo
A1: COTADO × ESTIMADO POR ETAPA
A2: # | B2: Etapa | C2: Estim. baixa | D2: Estim. alta | E2: Real / cotado | F2: Δ vs. alta | G2: Situação
A3: 1 | B3: Projetos, sondagem e aprovações | C3: =Etapas!C3 | D3: =Etapas!D3 | E3: =IF(Etapas!I3>0,Etapas!I3,Etapas!L3) | F3: =IF(E3=0,"",D3-E3) | G3: =IF(E3=0,"sem cotação",IF(E3>D3,"ACIMA da faixa",IF(E3<C3,"abaixo da faixa","dentro da faixa")))
A4: 2 | B4: Fundação (radier 103 m²) + muro de divisa 210 m² | C4: =Etapas!C4 | D4: =Etapas!D4 | E4: =IF(Etapas!I4>0,Etapas!I4,Etapas!L4) | F4: =IF(E4=0,"",D4-E4) | G4: =IF(E4=0,"sem cotação",IF(E4>D4,"ACIMA da faixa",IF(E4<C4,"abaixo da faixa","dentro da faixa")))
A5: 3 | B5: Estrutura metálica | C5: =Etapas!C5 | D5: =Etapas!D5 | E5: =IF(Etapas!I5>0,Etapas!I5,Etapas!L5) | F5: =IF(E5=0,"",D5-E5) | G5: =IF(E5=0,"sem cotação",IF(E5>D5,"ACIMA da faixa",IF(E5<C5,"abaixo da faixa","dentro da faixa")))
A6: 4 | B6: Paredes: Monolev (estrutural) + divisórias Lightwall | C6: =Etapas!C6 | D6: =Etapas!D6 | E6: =IF(Etapas!I6>0,Etapas!I6,Etapas!L6) | F6: =IF(E6=0,"",D6-E6) | G6: =IF(E6=0,"sem cotação",IF(E6>D6,"ACIMA da faixa",IF(E6<C6,"abaixo da faixa","dentro da faixa")))
A7: 5 | B7: Lajes de PISO (superior + sacada + técnica) | C7: =Etapas!C7 | D7: =Etapas!D7 | E7: =IF(Etapas!I7>0,Etapas!I7,Etapas!L7) | F7: =IF(E7=0,"",D7-E7) | G7: =IF(E7=0,"sem cotação",IF(E7>D7,"ACIMA da faixa",IF(E7<C7,"abaixo da faixa","dentro da faixa")))
A8: 6 | B8: Cobertura + lanternim | C8: =Etapas!C8 | D8: =Etapas!D8 | E8: =IF(Etapas!I8>0,Etapas!I8,Etapas!L8) | F8: =IF(E8=0,"",D8-E8) | G8: =IF(E8=0,"sem cotação",IF(E8>D8,"ACIMA da faixa",IF(E8<C8,"abaixo da faixa","dentro da faixa")))
A9: 7 | B9: Esquadrias e vidros | C9: =Etapas!C9 | D9: =Etapas!D9 | E9: =IF(Etapas!I9>0,Etapas!I9,Etapas!L9) | F9: =IF(E9=0,"",D9-E9) | G9: =IF(E9=0,"sem cotação",IF(E9>D9,"ACIMA da faixa",IF(E9<C9,"abaixo da faixa","dentro da faixa")))
A10: 8 | B10: Hidráulica + água quente + prep. PV | C10: =Etapas!C10 | D10: =Etapas!D10 | E10: =IF(Etapas!I10>0,Etapas!I10,Etapas!L10) | F10: =IF(E10=0,"",D10-E10) | G10: =IF(E10=0,"sem cotação",IF(E10>D10,"ACIMA da faixa",IF(E10<C10,"abaixo da faixa","dentro da faixa")))
A11: 9 | B11: Elétrica + automação + rede | C11: =Etapas!C11 | D11: =Etapas!D11 | E11: =IF(Etapas!I11>0,Etapas!I11,Etapas!L11) | F11: =IF(E11=0,"",D11-E11) | G11: =IF(E11=0,"sem cotação",IF(E11>D11,"ACIMA da faixa",IF(E11<C11,"abaixo da faixa","dentro da faixa")))
A12: 10 | B12: Climatização | C12: =Etapas!C12 | D12: =Etapas!D12 | E12: =IF(Etapas!I12>0,Etapas!I12,Etapas!L12) | F12: =IF(E12=0,"",D12-E12) | G12: =IF(E12=0,"sem cotação",IF(E12>D12,"ACIMA da faixa",IF(E12<C12,"abaixo da faixa","dentro da faixa")))
A13: 11 | B13: Acabamentos resinados (sem porcelanato) | C13: =Etapas!C13 | D13: =Etapas!D13 | E13: =IF(Etapas!I13>0,Etapas!I13,Etapas!L13) | F13: =IF(E13=0,"",D13-E13) | G13: =IF(E13=0,"sem cotação",IF(E13>D13,"ACIMA da faixa",IF(E13<C13,"abaixo da faixa","dentro da faixa")))
A14: 12 | B14: Gourmet (Invisacook, bancada, churrasqueira) | C14: =Etapas!C14 | D14: =Etapas!D14 | E14: =IF(Etapas!I14>0,Etapas!I14,Etapas!L14) | F14: =IF(E14=0,"",D14-E14) | G14: =IF(E14=0,"sem cotação",IF(E14>D14,"ACIMA da faixa",IF(E14<C14,"abaixo da faixa","dentro da faixa")))
A15: 13 | B15: Canteiro, limpeza e imprevistos (~8%) | C15: =Etapas!C15 | D15: =Etapas!D15 | E15: =IF(Etapas!I15>0,Etapas!I15,Etapas!L15) | F15: =IF(E15=0,"",D15-E15) | G15: =IF(E15=0,"sem cotação",IF(E15>D15,"ACIMA da faixa",IF(E15<C15,"abaixo da faixa","dentro da faixa")))

Sheet Revisões
A1: HISTÓRICO DE REVISÕES DO PROJETO
A2: Data | B2: Alteração | C2: Impacto
A3: 13/07/2026 | B3: Versão inicial da planilha (13 etapas, 116 itens) | C3: Faixa R$ 498–764 mil
A4: 13/07/2026 | B4: Orientação corrigida: frente NOROESTE (não norte) | C4: Fachada frontal recebe sol da tarde — verificar conforto
A5: 13/07/2026 | B5: Janelão da escada c/ peitoril 1,00 m (2,2 × 4,70) | C5: Vidro 12 → 10,5 m²
A6: 13/07/2026 | B6: Vão da garagem em altura total (chão → laje), viga na testada | C6: Perfil da viga a validar (altura útil limitada)
A7: 15/07/2026 | B7: Esclarecido: lajes = SÓ pisos. Forro nivelado gesso+EPS incluído | C7: +47 m² de forro (antes ausente do orçamento)
A8: 15/07/2026 | B8: Forro de MADEIRA no mezanino/vão duplo acompanhando o telhado | C8: +45 m² · R$ 8–16 mil (item premium)
A9: 15/07/2026 | B9: Divisórias do superior migradas de Monolev p/ Lightwall 2P 90 | C9: Monolev 421 → 340 m² · Etapa 4: R$ 120–170k → R$ 110–156k
A10: 16/07/2026 | B10: Faixa NE: área de luz até a fachada, portinha recuada 0,80 | C10: Telha 105 → 98 m² · estrutura 100 → 95 m²
A11: 16/07/2026 | B11: Parede cega entre Luz 1 e Luz 2 · Luz 1 = jardim de inverno | C11: +14 m² parede verde · +12 m² janelão · impermeabilizar divisa
A12: 16/07/2026 | B12: Cobertura: pórticos de viga cheia → 3 TRELIÇAS @3,25 m | C12: Aço 1,4 t → ~1,0 t · degrau do lanternim triangulado
A13: 16/07/2026 | B13: Terças: 6 → 4 linhas e Ue 150 → Ue 100 | C13: −170 kg · σ 61 MPa (24% de fy), flecha L/483
... A34: 24/07/2026 | B34: Área técnica passa a ser ABERTA (sem porta, portão-gradil) c/ escada marinheiro na parede da Luz 2 | C34: Garante ar para a bomba de calor (11,5 m³ fechados seriam insuficientes; fabricantes exigem 15-20 m³ ou ventilação permanente) · exige equipamentos IP65

Sheet Fornecedores
A1: CONSOLIDADO POR FORNECEDOR / EMPREITEIRO
A2: Uma linha por fornecedor cotado no site — quem fornece o quê, em qual etapa e por quanto.
A3: Fornecedor / empreiteiro | B3: Tipo | C3: Nº de cotações | D3: Total cotado | E3: Etapas envolvidas | F3: Itens
A4: Nenhum fornecedor cotado ainda. Cada cotação lançada no site cria/alimenta uma linha aqui.
